mrtool/__init__.py
mrtool/core/__init__.py
mrtool/core/cov_model.py
mrtool/core/data.py
mrtool/core/model.py
mrtool/core/plots.py
mrtool/core/utils.py
mrtool/cov_selection/__init__.py
mrtool/cov_selection/covfinder.py
mrtool-0.2.1.dist-info/LICENSE
mrtool-0.2.1.dist-info/METADATA
mrtool-0.2.1.dist-info/WHEEL
mrtool-0.2.1.dist-info/top_level.txt
mrtool-0.2.1.dist-info/RECORD
