Metadata-Version: 2.1
Name: mrtool
Version: 0.2.1
Summary: Featured nonlinear mixed effects model
Author-email: IHME Math Sciences <ihme.math.sciences@gmail.com>
License: BSD 2-Clause License
Project-URL: github, https://github.com/ihmeuw-msca/mrtool
Requires-Python: >=3.10
License-File: LICENSE
Requires-Dist: numpy
Requires-Dist: pandas
Requires-Dist: scipy
Requires-Dist: xspline <0.1.0
Requires-Dist: xarray
Requires-Dist: limetr <0.1.0
Requires-Dist: matplotlib
Provides-Extra: dev
Requires-Dist: pytest ; extra == 'dev'
Requires-Dist: pytest-mock ; extra == 'dev'
Provides-Extra: doc
Requires-Dist: sphinx ; extra == 'doc'
Requires-Dist: sphinx-autodoc-typehints ; extra == 'doc'
Requires-Dist: furo ; extra == 'doc'
